swanchain/__init__.py
swanchain/swanchain.py
tests/__init__.py
tests/swantest.py
swanchain-0.1.0.dist-info/METADATA
swanchain-0.1.0.dist-info/WHEEL
swanchain-0.1.0.dist-info/top_level.txt
swanchain-0.1.0.dist-info/RECORD
