Metadata-Version: 2.1
Name: swanchain
Version: 0.1.0
Summary: swanchain first Python library
Author: KashiwaByte
License: MIT
